excelminer/__init__.py
excelminer/api.py
excelminer/parallel.py
excelminer/reporting.py
excelminer/backends/__init__.py
excelminer/backends/base.py
excelminer/backends/calamine_backend.py
excelminer/backends/com_backend.py
excelminer/backends/ooxml_zip.py
excelminer/backends/openpyxl_backend.py
excelminer/backends/pivot_zip.py
excelminer/backends/powerquery_zip.py
excelminer/backends/vba_zip.py
excelminer/model/__init__.py
excelminer/model/entities.py
excelminer/model/graph.py
excelminer/model/normalize.py
excelminer/rationalization/__init__.py
excelminer/rationalization/distill.py
excelminer/rationalization/formulas.py
excelminer/rationalization/module.py
excelminer-0.0.4.dist-info/licenses/LICENSE
excelminer-0.0.4.dist-info/METADATA
excelminer-0.0.4.dist-info/WHEEL
excelminer-0.0.4.dist-info/top_level.txt
excelminer-0.0.4.dist-info/RECORD
