Metadata-Version: 2.4
Name: excelminer
Version: 0.0.4
Summary: Extract and normalize Excel workbook artifacts (sheets, connections, formulas) into a lightweight graph.
Author-email: Brent Carpenetti <brentwc.git@pm.me>
License: MIT License
Requires-Python: >=3.12
License-File: LICENSE
Requires-Dist: hostxray
Requires-Dist: oletools
Requires-Dist: openpyxl
Provides-Extra: calamine
Requires-Dist: pandas; extra == "calamine"
Requires-Dist: python-calamine; extra == "calamine"
Provides-Extra: com
Requires-Dist: pywin32; platform_system == "Windows" and extra == "com"
Provides-Extra: test
Requires-Dist: pytest>=7.0.0; extra == "test"
Requires-Dist: pytest-cov>=4.0.0; extra == "test"
Provides-Extra: dev
Requires-Dist: pytest>=7.0.0; extra == "dev"
Requires-Dist: pytest-cov>=4.0.0; extra == "dev"
Requires-Dist: black; extra == "dev"
Requires-Dist: flake8; extra == "dev"
Requires-Dist: mypy; extra == "dev"
Requires-Dist: isort; extra == "dev"
Requires-Dist: pre-commit; extra == "dev"
Provides-Extra: all
Requires-Dist: pandas; extra == "all"
Requires-Dist: python-calamine; extra == "all"
Requires-Dist: pywin32; platform_system == "Windows" and extra == "all"
Requires-Dist: pytest>=7.0.0; extra == "all"
Requires-Dist: pytest-cov>=4.0.0; extra == "all"
Requires-Dist: black; extra == "all"
Requires-Dist: flake8; extra == "all"
Requires-Dist: mypy; extra == "all"
Requires-Dist: isort; extra == "all"
Requires-Dist: pre-commit; extra == "all"
Dynamic: license-file
